salesforce_timecard/__init__.py
salesforce_timecard/cli.py
salesforce_timecard/core.py
salesforce_timecard/utils.py
salesforce_timecard-1.1.9.dist-info/LICENSE
salesforce_timecard-1.1.9.dist-info/METADATA
salesforce_timecard-1.1.9.dist-info/WHEEL
salesforce_timecard-1.1.9.dist-info/entry_points.txt
salesforce_timecard-1.1.9.dist-info/top_level.txt
salesforce_timecard-1.1.9.dist-info/RECORD
