Metadata-Version: 2.1
Name: salesforce-timecard
Version: 1.1.9
Summary: PSE Timecard CLI
Home-page: https://github.com/giuliocalzolari/salesforce-timecard
Author: giuliocalzolari
Author-email: giuliocalzolari@users.noreply.github.com
Maintainer: giuliocalzolari
Maintainer-email: giuliocalzolari@users.noreply.github.com
License: WTFPL
Keywords: python salesforce timecard cli
Platform: UNKNOWN
Classifier: Development Status :: 4 - Beta
Classifier: Intended Audience :: Developers
Classifier: Natural Language :: English
Classifier: Environment :: Console
Classifier: Programming Language :: Python :: 3.6
Requires-Dist: simple-salesforce
Requires-Dist: click
Requires-Dist: tabulate
Requires-Dist: click-aliases
Requires-Dist: setupext-janitor
Requires-Dist: pyyaml
Requires-Dist: keyring
